subconvert/__init__.py
subconvert/apprunner.py
subconvert/resources.py
subconvert/cli/MainApp.py
subconvert/cli/__init__.py
subconvert/cli/syncparse.py
subconvert/gui/DataModel.py
subconvert/gui/Detail.py
subconvert/gui/FileDialogs.py
subconvert/gui/FrameTimeSpinBox.py
subconvert/gui/GuiApp.py
subconvert/gui/MainWindow.py
subconvert/gui/OffsetDialog.py
subconvert/gui/PropertyFileEditor.py
subconvert/gui/SubModel.py
subconvert/gui/SubtitleCommands.py
subconvert/gui/SubtitleTabs.py
subconvert/gui/SubtitleWindow.py
subconvert/gui/ToolBox.py
subconvert/gui/VideoWidget.py
subconvert/gui/_VideoWidget.py
subconvert/gui/_VideoWidgetNoMultimedia.py
subconvert/gui/__init__.py
subconvert/gui/tools/Details.py
subconvert/gui/tools/History.py
subconvert/gui/tools/Synchronizer.py
subconvert/gui/tools/__init__.py
subconvert/locale/pl/LC_MESSAGES/subconvert.mo
subconvert/parsing/Core.py
subconvert/parsing/Formats.py
subconvert/parsing/FrameTime.py
subconvert/parsing/Offset.py
subconvert/parsing/__init__.py
subconvert/utils/Alias.py
subconvert/utils/Encodings.py
subconvert/utils/Locale.py
subconvert/utils/PropertyFile.py
subconvert/utils/SubException.py
subconvert/utils/SubFile.py
subconvert/utils/SubSettings.py
subconvert/utils/SubtitleData.py
subconvert/utils/SubtitleSearch.py
subconvert/utils/__init__.py
subconvert/utils/cleanup.py
subconvert/utils/version.py
subconvert-3.0.0.data/data/share/applications/subconvert.desktop
subconvert-3.0.0.data/data/share/icons/hicolor/128x128/apps/subconvert.png
subconvert-3.0.0.data/data/share/icons/hicolor/16x16/apps/subconvert.png
subconvert-3.0.0.data/data/share/icons/hicolor/22x22/apps/subconvert.png
subconvert-3.0.0.data/data/share/icons/hicolor/256x256/apps/subconvert.png
subconvert-3.0.0.data/data/share/icons/hicolor/32x32/apps/subconvert.png
subconvert-3.0.0.data/data/share/icons/hicolor/48x48/apps/subconvert.png
subconvert-3.0.0.dist-info/DESCRIPTION.rst
subconvert-3.0.0.dist-info/METADATA
subconvert-3.0.0.dist-info/RECORD
subconvert-3.0.0.dist-info/WHEEL
subconvert-3.0.0.dist-info/entry_points.txt
subconvert-3.0.0.dist-info/metadata.json
subconvert-3.0.0.dist-info/top_level.txt
