Metadata-Version: 2.0
Name: subconvert
Version: 3.0.0
Summary: Movie subtitles converter
Home-page: https://gitlab.com/mgoral/subconvert
Author: Michał Góral
Author-email: dev@mgoral.org
License: GPLv3+
Platform: linux
Classifier: Development Status :: 6 - Mature
Classifier: Environment :: Console
Classifier: Environment :: X11 Applications :: Qt
Classifier: Intended Audience :: End Users/Desktop
Classifier: License :: OSI Approved :: GNU General Public License v3 or later (GPLv3+)
Classifier: Natural Language :: English
Classifier: Operating System :: POSIX
Classifier: Programming Language :: Python :: 3 :: Only
Classifier: Programming Language :: Python :: 3.4
Classifier: Programming Language :: Python :: 3.5
Classifier: Programming Language :: Python :: 3.6
Classifier: Topic :: Utilities
Requires-Dist: PyQt5 (==5.9)
Requires-Dist: chardet (==3.0.4)
Requires-Dist: pymediainfo (==2.1.9)
Requires-Dist: python-mpv (==0.3.2)
